{
  "lesson_meta": {
    "title": "காற்று",
    "unit": "11",
    "grade": "8",
    "term": "பொது",
    "subject": "science",
    "code": "sci_8_l11"
  },
  "quiz": {
    "questions": [
      {
        "question": "காற்றில் அதிக அளவில் காணப்படும் வாயு எது?",
        "options": [
          "ஆக்சிஜன்",
          "கார்பன் டைஆக்சைடு",
          "நைட்ரஜன்",
          "ஆர்கான்"
        ],
        "answer": 2,
        "explanation": "காற்றில் 78.09% நைட்ரஜனும், 20.95% ஆக்சிஜனும், 0.93% ஆர்கானும், 0.04% கார்பன் டைஆக்சைடும் அடங்கியுள்ளன. எனவே நைட்ரஜன் அதிக அளவில் உள்ளது."
      },
      {
        "question": "காற்றில் உள்ள ஆர்கான் மற்றும் கார்பன் டைஆக்சைடின் சதவீத அளவுகள் முறையே:",
        "options": [
          "0.93% மற்றும் 0.04%",
          "0.04% மற்றும் 0.93%",
          "20.95% மற்றும் 0.03%",
          "78.09% மற்றும் 0.04%"
        ],
        "answer": 0,
        "explanation": "காற்றில் 0.93% ஆர்கானும், 0.04% கார்பன் டைஆக்சைடும் காணப்படுகின்றன."
      },
      {
        "question": "தாவரங்கள் எந்த வாயுவை ஒளிச்சேர்க்கைக்குப் பயன்படுத்திக் கொள்கின்றன?",
        "options": [
          "ஆக்சிஜன்",
          "நைட்ரஜன்",
          "கார்பன் டைஆக்சைடு",
          "கார்பன் மோனாக்சைடு"
        ],
        "answer": 2,
        "explanation": "தாவரங்கள் கார்பன் டைஆக்சைடை ஒளிச்சேர்க்கைக்குப் பயன்படுத்திக் கொண்டு ஆக்சிஜனை வெளியிடுகின்றன."
      },
      {
        "question": "1772-ஆம் ஆண்டு ஆக்சிஜனைக் கண்டறிந்த ஸ்வீடன் நாட்டு வேதியியலாளர் யார்?",
        "options": [
          "ஜோசப் பிரிஸ்ட்லி",
          "C.W. ஷீலே",
          "லவாய்சியர்",
          "டால்டன்"
        ],
        "answer": 1,
        "explanation": "1772ஆம் ஆண்டு ஸ்வீடன் நாட்டைச் சேர்ந்த வேதியியலாளர் C.W.ஷீலே ஆக்சிஜனைக் கண்டறிந்தார்."
      },
      {
        "question": "ஆக்சிஜனுக்கு 'நெருப்புக்காற்று' (Fire Air) மற்றும் 'அத்தியாவசியமான உயிர்' என்று பெயரிட்டவர் யார்?",
        "options": [
          "லவாய்சியர்",
          "ஜோசப் பிரிஸ்ட்லி",
          "C.W. ஷீலே",
          "ஐசக் நியூட்டன்"
        ],
        "answer": 2,
        "explanation": "C.W.ஷீலே ஆக்சிஜனைக் கண்டறிந்தபோது அது எரிதலுக்குத் துணை புரிந்ததால் அதனை நெருப்புக்காற்று என்றும், அத்தியாவசியமான உயிர் என்றும் அழைத்தார்."
      },
      {
        "question": "1774-ஆம் ஆண்டு தனது தனிப்பட்ட முயற்சியால் ஆக்சிஜனைக் கண்டறிந்த பிரிட்டன் அறிவியலாளர் யார்?",
        "options": [
          "ஜோசப் பிரிஸ்ட்லி",
          "லவாய்சியர்",
          "C.W. ஷீலே",
          "வில்லியம் ராம்சே"
        ],
        "answer": 0,
        "explanation": "பிரிட்டன் அறிவியலாளர் ஜோசப் பிரிஸ்ட்லி என்பவர் 1774ஆம் ஆண்டு தனது தனிப்பட்ட முயற்சியால் ஆக்சிஜனைக் கண்டறிந்தார்."
      },
      {
        "question": "ஆக்சிஜன் (Oxygen) என்ற பெயரைச் சூட்டிய அறிவியலாளர் யார்?",
        "options": [
          "C.W. ஷீலே",
          "ஜோசப் பிரிஸ்ட்லி",
          "லவாய்சியர்",
          "அலெக்சாண்டர் பிளெமிங்"
        ],
        "answer": 2,
        "explanation": "லவாய்சியர் எனும் அறிவியலாளர் இதற்கு ஆக்சிஜன் என்று பெயரிட்டார்."
      },
      {
        "question": "கிரேக்க மொழியில் 'ஆக்சிஜன்ஸ்' (Oxygenes) என்பதன் பொருள் என்ன?",
        "options": [
          "உயிர் கொடுக்கும் வாயு",
          "அமில உருவாக்கி",
          "நெருப்பை உருவாக்கும் வாயு",
          "வாழ்வு இல்லாதது"
        ],
        "answer": 1,
        "explanation": "கிரேக்கமொழியில் ஆக்சிஜன்ஸ் என்றால் ‘அமில உருவாக்கி’ என்று பொருள். முற்கால வேதியியலாளர்கள் அமிலம் தயாரிக்க ஆக்சிஜன் அவசியம் எனக் கருதினர்."
      },
      {
        "question": "அண்டத்தில் (Universe) பரவலாக ஹைட்ரஜன் மற்றும் ஹீலியத்திற்கு அடுத்தபடியாக மூன்றாவது இடத்தில் காணப்படும் தனிமம் எது?",
        "options": [
          "நைட்ரஜன்",
          "கார்பன்",
          "ஆக்சிஜன்",
          "இரும்பு"
        ],
        "answer": 2,
        "explanation": "ஹைட்ரஜன் மற்றும் ஹீலியத்திற்கு அடுத்தபடியாக இந்த அண்டத்தில் பரவலாக மூன்றாவதாகக் காணப்படும் தனிமம் ஆக்சிஜன்."
      },
      {
        "question": "வளிமண்டலத்தின் மேல் அடுக்குகளில் ஆக்சிஜன் மூவணு மூலக்கூறாக (O3) எவ்வாறு காணப்படுகிறது?",
        "options": [
          "மீத்தேன்",
          "ஓசோன்",
          "நீராவி",
          "குளோரோபுளுரோகார்பன்"
        ],
        "answer": 1,
        "explanation": "வளிமண்டலத்தின் மேல் அடுக்குகளில் ஆக்சிஜன் ஓசோன் எனப்படும் மூவணு மூலக்கூறாக (O3) உள்ளது."
      },
      {
        "question": "புவியோட்டில் (Earth's crust) அதிக சதவீதம் உள்ள தனிமம் எது?",
        "options": [
          "சிலிக்கான் (Si)",
          "அலுமினியம் (Al)",
          "இரும்பு (Fe)",
          "ஆக்சிஜன் (O)"
        ],
        "answer": 3,
        "explanation": "புவியோட்டில் ஆக்சிஜன் 46.6% சதவிகிதம் உள்ளது. இதுவே புவியோட்டில் அதிகம் உள்ள தனிமமாகும்."
      },
      {
        "question": "சிலிக்கேட்டுகள், கார்பனேட்டுகள் மற்றும் ஆக்சைடுகள் வடிவிலுள்ள தாதுக்களில் ஆக்சிஜனின் சதவீதம் எவ்வளவு?",
        "options": [
          "88 – 90 %",
          "60 – 70 %",
          "45 – 50 %",
          "21 %"
        ],
        "answer": 2,
        "explanation": "தாதுக்களில் இணைந்த நிலையில் ஆக்சிஜனின் சதவீதம் 45 – 50 % ஆகும்."
      },
      {
        "question": "தாவரங்கள் மற்றும் விலங்குகளில் இணைந்த நிலையில் ஆக்சிஜன் எவ்வளவு சதவீதம் காணப்படுகிறது?",
        "options": [
          "21 %",
          "88 – 90 %",
          "45 – 50 %",
          "60 – 70 %"
        ],
        "answer": 3,
        "explanation": "தாவரங்கள் மற்றும் விலங்குகளில் இணைந்த நிலையில் ஆக்சிஜன் 60 – 70 % காணப்படுகிறது."
      },
      {
        "question": "ஆக்சிஜனின் இயற்பியல் பண்புகளில் தவறானது எது?",
        "options": [
          "நிறமற்ற, மணமற்ற, சுவையற்ற வாயு",
          "வெப்பம் மற்றும் மின்சாரத்தை எளிதில் கடத்தும்",
          "காற்றை விட கனமானது",
          "எரிதலுக்குத் துணைபுரியும்"
        ],
        "answer": 1,
        "explanation": "ஆக்சிஜன் வெப்பம் மற்றும் மின்சாரத்தை எளிதில் கடத்தாது என்பதே சரியான பண்பாகும்."
      },
      {
        "question": "ஆக்சிஜன் நைட்ரஜனை விட எத்தனை மடங்கு நீரில் அதிகமாகக் கரையும் தன்மை உடையது?",
        "options": [
          "இருமடங்கு",
          "மும்மடங்கு",
          "நான்கு மடங்கு",
          "பாதி அளவு"
        ],
        "answer": 0,
        "explanation": "ஆக்சிஜனானது நைட்ரஜனைவிட இருமடங்கு நீரில் அதிகமாகக் கரையும் தன்மை உடையது. இதுவே நீர்வாழ் உயிரினங்கள் வாழ உதவுகிறது."
      },
      {
        "question": "ஆக்சிஜனின் எரிதல் பண்பு குறித்து சரியான கூற்று எது?",
        "options": [
          "அது தனித்து எரியும் தன்மை கொண்டது",
          "அது தனித்து எரியும் தன்மை அற்றது, ஆனால் பிற பொருள்களின் எரிதலுக்குத் துணை புரியும்",
          "அது எரியாது மற்றும் எரிதலுக்குத் துணைபுரியாது",
          "அது எரிதைக் கட்டுப்படுத்தும் வாயுவாகும்"
        ],
        "answer": 1,
        "explanation": "ஆக்சிஜன் தனித்து எரியும் தன்மை அற்றது. ஆனால், இது பிற பொருள்களின் எரிதலுக்குத் துணை புரியும்."
      },
      {
        "question": "உலோகங்கள் ஆக்சிஜனுடன் வினைபுரிந்து உருவாக்கும் உலோக ஆக்சைடுகள் பொதுவாக எத்தன்மை உடையவை?",
        "options": [
          "அமிலத்தன்மை",
          "காரத்தன்மை",
          "நடுநிலைத்தன்மை",
          "ஈரியல்புத் தன்மை"
        ],
        "answer": 1,
        "explanation": "உலோகங்களுடன் ஆக்சிஜன் வினைபுரிந்து அவற்றின் உலோக ஆக்சைடுகளைத் தருகிறது. இவை பொதுவாக காரத்தன்மை உடையவை."
      },
      {
        "question": "அறை வெப்பநிலையிலேயே ஆக்சிஜனுடன் வினைபுரியும் உலோகம் எது?",
        "options": [
          "மெக்னீசியம்",
          "இரும்பு",
          "தாமிரம்",
          "பொட்டாசியம்"
        ],
        "answer": 3,
        "explanation": "பொட்டாசியம் (K) அறை வெப்பநிலையிலேயே ஆக்சிஜனுடன் வினைபுரிந்து பொட்டாசியம் ஆக்சைடை (K2O) உருவாக்குகிறது."
      },
      {
        "question": "அதிக வெப்பத்திலும் ஆக்சிஜனுடன் வினைபுரியாத உலோகங்கள் எவை?",
        "options": [
          "இரும்பு மற்றும் தாமிரம்",
          "தங்கம் மற்றும் பிளாட்டினம்",
          "கால்சியம் மற்றும் மெக்னீசியம்",
          "வெள்ளி மற்றும் தாமிரம்"
        ],
        "answer": 1,
        "explanation": "தங்கம் (Au) மற்றும் பிளாட்டினம் (Pt) ஆகிய உலோகங்கள் அதிக வெப்பத்திலும் ஆக்சிஜனுடன் வினை புரியாது."
      },
      {
        "question": "அலோகங்கள் ஆக்சிஜனுடன் வினைபுரிந்து எத்தன்மை வாய்ந்த ஆக்சைடுகளை உருவாக்குகின்றன?",
        "options": [
          "காரத்தன்மை",
          "அமிலத்தன்மை",
          "நடுநிலைத்தன்மை",
          "எந்த ஆக்சைடும் உருவாவதில்லை"
        ],
        "answer": 1,
        "explanation": "அலோகங்களுடன் ஆக்சிஜன் வினைபுரிந்து அமிலத்தன்மை வாய்ந்த அலோக ஆக்சைடுகளை உருவாக்குகின்றது."
      },
      {
        "question": "பாஸ்பரஸ் ஆக்சிஜனுடன் எரியும்போது வெளிவரும் வெண்புகை (White smoke) எதனால் உருவாகிறது?",
        "options": [
          "பாஸ்பரஸ் டிரைஆக்சைடு",
          "பாஸ்பரஸ் பென்டாக்சைடு",
          "பாஸ்பாரிக் அமிலம்",
          "பாஸ்பீன்"
        ],
        "answer": 1,
        "explanation": "பாஸ்பரஸ் ஆக்சிஜனுடன் எரிந்து பாஸ்பரஸ் பென்டாக்சைடு (P2O5) என்ற வெண்புகையைத் தருகிறது."
      },
      {
        "question": "ஹைட்ரோகார்பன்கள் ஆக்சிஜனுடன் எரியும்போது உருவாகும் வினைபொருள்கள் எவை?",
        "options": [
          "கார்பன் மோனாக்சைடு மற்றும் ஹைட்ரஜன்",
          "கார்பன் டைஆக்சைடு, நீராவி, வெப்ப மற்றும் ஒளி ஆற்றல்",
          "கார்பன் மற்றும் ஆக்சிஜன்",
          "கார்பானிக் அமிலம்"
        ],
        "answer": 1,
        "explanation": "ஆக்சிஜன் ஹைட்ரோகார்பன்களுடன் வினைபுரிந்து கார்பன் டைஆக்சைடையும், நீராவியையும், வெப்ப மற்றும் ஒளி ஆற்றலையும் தருகிறது."
      },
      {
        "question": "துரு (Rust) என்பதன் வேதிப்பெயர் என்ன?",
        "options": [
          "நீரேறிய தாமிர ஆக்சைடு",
          "நீரேறிய இரும்பு (II) ஆக்சைடு / இரும்பு (III) ஆக்சைடு",
          "கால்சியம் கார்பனேட்",
          "இரும்பு சல்பைடு"
        ],
        "answer": 1,
        "explanation": "துரு என்பது நீரேறிய இரும்பு ஆக்சைடு ஆகும். (புத்தகத்தில் Fe2O3.XH2O கொடுக்கப்பட்டுள்ளது)."
      },
      {
        "question": "துருப்பிடித்தல் வினையில் 'X' H2O என்பதில் X எதைக் குறிக்கிறது?",
        "options": [
          "இரும்பின் அணுக்களின் எண்ணிக்கையை",
          "ஆக்சிஜனின் அளவை",
          "வேறுபட்ட நீர் மூலக்கூறுகளின் எண்ணிக்கையை",
          "வினையூக்கியின் அளவை"
        ],
        "answer": 2,
        "explanation": "X என்பது வேறுபட்ட நீர் மூலக்கூறுகளின் எண்ணிக்கையைக் குறிக்கிறது."
      },
      {
        "question": "உலோகங்களை வெட்டவும் இணைக்கவும் (வெல்டிங்) பயன்படும் வாயு கலவை எது?",
        "options": [
          "ஆக்சி-நைட்ரஜன்",
          "ஆக்சி-அசிட்டிலின்",
          "ஹைட்ரஜன்-நைட்ரஜன்",
          "கார்பன்-ஆக்சிஜன்"
        ],
        "answer": 1,
        "explanation": "உலோகங்களை வெட்டவும் இணைக்கவும் ஆக்சி-அசிட்டிலின் உருளைகளில் ஆக்சிஜன் பயன்படுகிறது."
      },
      {
        "question": "எஃகிலுள்ள (Steel) எந்த மாசை நீக்க ஆக்சிஜன் பயன்படுகிறது?",
        "options": [
          "கந்தக மாசு",
          "கார்பன் மாசு",
          "பாஸ்பரஸ் மாசு",
          "சிலிக்கான் மாசு"
        ],
        "answer": 1,
        "explanation": "எஃகிலுள்ள கார்பன் மாசை நீக்க ஆக்சிஜன் பயன்படுகிறது."
      },
      {
        "question": "வெடிபொருள் தயாரிக்க கரித்தூளுடன் எந்த வாயு இணைக்கப்படுகிறது?",
        "options": [
          "நைட்ரஜன்",
          "கார்பன் டைஆக்சைடு",
          "ஆக்சிஜன்",
          "ஆர்கான்"
        ],
        "answer": 2,
        "explanation": "கரித்தூளுடன் ஆக்சிஜனை இணைத்து வெடிபொருள் தயாரிக்கப்படுகிறது."
      },
      {
        "question": "அனைத்து உயிரினங்களின் அடிப்படைக் கட்டமைப்புப் பொருள்களான புரோட்டீன்கள் மற்றும் நியூக்ளிக் அமிலங்களில் உள்ள முக்கியத் தனிமம் எது?",
        "options": [
          "கார்பன்",
          "நைட்ரஜன்",
          "ஆக்சிஜன்",
          "கால்சியம்"
        ],
        "answer": 1,
        "explanation": "புரோட்டீன்கள் மற்றும் நியூக்ளிக் அமிலங்களில் முக்கியத் தனிமமாக நைட்ரஜன் உள்ளது."
      },
      {
        "question": "1772-ஆம் ஆண்டு முதன்முதலில் காற்றிலிருந்து நைட்ரஜனைப் பிரித்தெடுத்தவர் யார்?",
        "options": [
          "ஜோசப் பிரிஸ்ட்லி",
          "ஆன்டன் லவாய்சியர்",
          "கார்ல் வில்கம் ஷீலே",
          "ஜான் டால்டன்"
        ],
        "answer": 2,
        "explanation": "1772ஆம் ஆண்டு ஸ்வீடன் நாட்டைச் சேர்ந்த கார்ல் வில்கம் ஷீலே என்பவரால் முதன்முதலில் காற்றிலிருந்து நைட்ரஜன் பிரித்தெடுக்கப்பட்டது."
      },
      {
        "question": "நைட்ரஜனுக்கு 'அசோட்' (Azote) என்ற பெயரைப் பரிந்துரைத்தவர் யார்?",
        "options": [
          "கார்ல் வில்கம் ஷீலே",
          "ஜோசப் பிரிஸ்ட்லி",
          "ஆன்டன் லவாய்சியர்",
          "மெண்டலீவ்"
        ],
        "answer": 2,
        "explanation": "ஆன்டன் லவாய்சியர் இதற்கு அசோட் என்ற பெயரைப் பரிந்துரைத்தார்."
      },
      {
        "question": "கிரேக்க மொழியில் 'அசோட்' (Azote) என்றால் என்ன பொருள்?",
        "options": [
          "நெருப்புக்காற்று",
          "அமில உருவாக்கி",
          "வாழ்வு இல்லாதது",
          "உயிர் கொடுப்பது"
        ],
        "answer": 2,
        "explanation": "கிரேக்க மொழியில் அசோட் என்றால் வாழ்வு இல்லாதது என்று பொருள்படும்."
      },
      {
        "question": "மனித உடலில் அதிக அளவில் காணப்படும் தனிமங்களில் நைட்ரஜனின் இடம் என்ன?",
        "options": [
          "முதலாவது",
          "இரண்டாவது",
          "மூன்றாவது",
          "நான்காவது"
        ],
        "answer": 3,
        "explanation": "மனித உடலில் நான்காவதாக அதிக அளவில் காணப்படும் தனிமம் நைட்ரஜன் ஆகும். இது மொத்த நிறையில் 3% உள்ளது."
      },
      {
        "question": "நமது அண்டத்தில் (Universe) பரவலாக நைட்ரஜன் எத்தனையாவது இடத்தில் காணப்படுகிறது?",
        "options": [
          "மூன்றாவது",
          "நான்காவது",
          "ஐந்தாவது",
          "ஏழாவது"
        ],
        "answer": 3,
        "explanation": "நமது அண்டத்தில் பரவலாக ஏழாவது இடத்தில் காணப்படும் தனிமமாகவும் நைட்ரஜன் உள்ளது."
      },
      {
        "question": "சனிக்கோளின் துணைக்கோளான டைட்டனின் (Titan) வாயுமண்டலத்தில் 98% அளவு உள்ள வாயு எது?",
        "options": [
          "மீத்தேன்",
          "நைட்ரஜன்",
          "ஆக்சிஜன்",
          "கார்பன் டைஆக்சைடு"
        ],
        "answer": 1,
        "explanation": "சனிக்கோளின் பெரிய துணைக் கோளான டைட்டனின் வாயுமண்டலத்தில் 98% நைட்ரஜன் உள்ளது."
      },
      {
        "question": "நைட்டர் (Niter) என அழைக்கப்படும் தாதுவின் வேதிப்பெயர் என்ன?",
        "options": [
          "சோடியம் நைட்ரேட்",
          "பொட்டாசியம் நைட்ரேட்",
          "கால்சியம் நைட்ரேட்",
          "அம்மோனியம் நைட்ரேட்"
        ],
        "answer": 1,
        "explanation": "நைட்டர் என்பது பொட்டாசியம் நைட்ரேட் (KNO3) ஆகும்."
      },
      {
        "question": "சில்லி சால்ட் பீட்டர் (Chile saltpeter) என அழைக்கப்படும் தாது எது?",
        "options": [
          "சோடியம் நைட்ரேட்",
          "பொட்டாசியம் நைட்ரேட்",
          "சோடியம் குளோரைடு",
          "கால்சியம் கார்பனேட்"
        ],
        "answer": 0,
        "explanation": "சில்லி சால்ட் பீட்டர் என்பது சோடியம் நைட்ரேட் (NaNO3) ஆகும்."
      },
      {
        "question": "நைட்ரஜனின் இயற்பியல் பண்புகளில் தவறானது எது?",
        "options": [
          "நீரில் சிறிதளவே கரையும்",
          "காற்றை விட சிறிது கனமானது",
          "உறையும்பொழுது வெண்மையான திண்மமாக மாறுகிறது",
          "லிட்மஸுடன் நடுநிலைத் தன்மையுடன் காணப்படுகிறது"
        ],
        "answer": 1,
        "explanation": "நைட்ரஜன் காற்றை விட சிறிதளவு இலேசானது (கனமானது அல்ல)."
      },
      {
        "question": "நைட்ரஜனின் எரிதல் பண்பு குறித்து சரியான கூற்று எது?",
        "options": [
          "தானாக எரியும், ஆனால் எரிதலுக்குத் துணைபுரியாது",
          "தானாக எரியாது, ஆனால் எரிதலுக்குத் துணைபுரியும்",
          "தானாக எரிவதில்லை மற்றும் எரிதலுக்குத் துணைபுரிவதும் இல்லை",
          "எரிதலுக்கு மிகச் சிறந்த ஊக்கியாகும்"
        ],
        "answer": 2,
        "explanation": "நைட்ரஜன் தானாக எரிவதில்லை; மற்றும் எரிதலுக்குத் துணைபுரிவதும் இல்லை. எனவே இது எரிதலைக் கட்டுப்படுத்துகிறது."
      },
      {
        "question": "உலோகங்கள் உயர் வெப்பநிலையில் நைட்ரஜனுடன் வினைபுரிந்து எவற்றைத் தருகின்றன?",
        "options": [
          "உலோக ஆக்சைடுகள்",
          "உலோக நைட்ரைடுகள்",
          "உலோக கார்பனேட்டுகள்",
          "உலோக சல்பேட்டுகள்"
        ],
        "answer": 1,
        "explanation": "உலோகங்களுடன் நைட்ரஜன் உயர் வெப்பநிலையில் வினைபுரிந்து அவற்றின் உலோக நைட்ரைடுகளைத் தருகிறது."
      },
      {
        "question": "ஹைட்ரஜனும் நைட்ரஜனும் அதிக வெப்பநிலையில் வினைபுரிந்து உருவாகும் சேர்மம் எது?",
        "options": [
          "நைட்ரிக் அமிலம்",
          "அம்மோனியா",
          "நைட்ரஸ் ஆக்சைடு",
          "ஹைட்ராசின்"
        ],
        "answer": 1,
        "explanation": "3H2 + N2 -> 2NH3 (அம்மோனியா)."
      },
      {
        "question": "குளிர்சாதனப் பெட்டிகளில் குளிரூட்டியாக (Refrigerant) பயன்படுவது எது?",
        "options": [
          "திரவ ஆக்சிஜன்",
          "திரவ நைட்ரஜன்",
          "திண்ம கார்பன் டைஆக்சைடு",
          "திரவ ஹைட்ரஜன்"
        ],
        "answer": 1,
        "explanation": "திரவ நைட்ரஜன் குளிர்சாதனப் பெட்டிகளில் குளிரூட்டியாக பயன்படுகிறது."
      },
      {
        "question": "அம்மோனியா தயாரிப்பில் பயன்படும் முறை எது?",
        "options": [
          "சால்வே முறை",
          "ஹேபர் முறை",
          "கான்டாக்ட் முறை",
          "ஆஸ்ட்வால்டு முறை"
        ],
        "answer": 1,
        "explanation": "அம்மோனியா தயாரிப்பில் ஹேபர் முறை (Haber process) பயன்படுகிறது."
      },
      {
        "question": "வாகனங்களின் டயர்களில் நிரப்ப, தற்காலத்தில் காற்றிற்குப் பதிலாக எந்த வாயு அதிகளவில் பயன்படுத்தப்படுகிறது?",
        "options": [
          "ஆர்கான்",
          "நைட்ரஜன்",
          "ஹீலியம்",
          "கார்பன் டைஆக்சைடு"
        ],
        "answer": 1,
        "explanation": "வாகனங்களின் டயர்களில் நிரப்ப நைட்ரஜன் பயன்படுகிறது."
      },
      {
        "question": "வெப்பநிலைமானிகளில் உள்ள பாதரசம் ஆவியாகாமல் தடுக்க, பாதரசத்திற்கு மேலுள்ள வெற்றிடத்தை நிரப்ப எந்த வாயு பயன்படுகிறது?",
        "options": [
          "ஆக்சிஜன்",
          "நைட்ரஜன்",
          "கார்பன் டைஆக்சைடு",
          "ஹைட்ரஜன்"
        ],
        "answer": 1,
        "explanation": "வெப்பநிலைமானிகளில் பாதரசம் ஆவியாகாமல் தடுக்க வெற்றிடத்தை நிரப்ப நைட்ரஜன் பயன்படுகிறது."
      },
      {
        "question": "TNT, நைட்ரோகிளிசரின் போன்ற வெடிபொருள்கள் தயாரிக்கப் பயன்படும் தனிமம் எது?",
        "options": [
          "கார்பன்",
          "ஆக்சிஜன்",
          "நைட்ரஜன்",
          "பாஸ்பரஸ்"
        ],
        "answer": 2,
        "explanation": "TNT (ட்ரைநைட்ரோடொலுவின்), நைட்ரோகிளிசரின் போன்ற வெடிபொருள்கள் தயாரிக்க நைட்ரஜன் பயன்படுகிறது."
      },
      {
        "question": "காற்றில் உள்ள தனிம நைட்ரஜனைத் தாவரங்கள் நேரடியாகப் பயன்படுத்த இயலுமா?",
        "options": [
          "ஆம், இலைத் துளைகள் மூலம் உறிஞ்சும்",
          "இல்லை, தங்களுக்குத் தேவையான நைட்ரேட்டுகளாக மாற்றியே பயன்படுத்தும்",
          "ஆம், வேர்கள் மூலம் வாயுவை உறிஞ்சும்",
          "தாவரங்களுக்கு நைட்ரஜன் தேவையில்லை"
        ],
        "answer": 1,
        "explanation": "காற்றில் உள்ள தனிம நைட்ரஜனை தாவரங்கள் நேரடியாகப் பயன்படுத்த இயலாது. அவற்றுக்கு நீரில் கரையும் நைட்ரஜன் சேர்மங்கள் (நைட்ரேட்டுகள்) தேவை."
      },
      {
        "question": "காற்றில் உள்ள நைட்ரஜனை நைட்ரஜன் சேர்மங்களாக மாற்றும் முறை எவ்வாறு அழைக்கப்படுகிறது?",
        "options": [
          "நைட்ரஜன் சுழற்சி",
          "நைட்ரஜன் நிலைநிறுத்தம்",
          "அம்மோனியாவாக்கம்",
          "நைட்ரஜனாக்கம்"
        ],
        "answer": 1,
        "explanation": "காற்றில் உள்ள நைட்ரஜனை நைட்ரஜன் சேர்மங்களாக மாற்றும் முறை நைட்ரஜன் நிலைநிறுத்தம் (Nitrogen fixation) எனப்படும்."
      },
      {
        "question": "கார்பன் டைஆக்சைடு வாயுவின் வேதி வாய்ப்பாடு என்ன?",
        "options": [
          "CO",
          "C2O",
          "CO2",
          "H2CO3"
        ],
        "answer": 2,
        "explanation": "கார்பன் டைஆக்சைடு CO2 என்ற வாய்ப்பாட்டால் குறிக்கப்படுகிறது (ஒரு கார்பன் மற்றும் இரண்டு ஆக்சிஜன் அணுக்கள்)."
      },
      {
        "question": "பூமியின் வளிமண்டலத்தில் கார்பன் டைஆக்சைடு வாயு எவ்வளவு சதவீதம் உள்ளது?",
        "options": [
          "0.04%",
          "0.03%",
          "0.3%",
          "3%"
        ],
        "answer": 1,
        "explanation": "புத்தகத்தின் 11.3.1 பிரிவின்படி, பூமியின் வளிமண்டலத்தில் கார்பன் டைஆக்சைடு வாயு 0.03% உள்ளது. (அறிமுகத்தில் 0.04% என உள்ளது, இரண்டுமே ஏற்புடையவை, ஆனால் 0.03% என்பது பிரிவில் நேரடியாகக் கொடுக்கப்பட்டுள்ளது)."
      },
      {
        "question": "இயற்கையில் காணப்படும் பெரும்பாலான கார்பன் டைஆக்சைடு எதன் மூலம் வெளியேற்றப்படுகிறது?",
        "options": [
          "தாவரங்களின் சுவாசம்",
          "எரிமலையிலிருந்து வரும் மேக்மா",
          "விலங்குகளின் சுவாசம்",
          "படிம எரிபொருள்கள் எரிதல்"
        ],
        "answer": 1,
        "explanation": "இயற்கையில் காணப்படும் பெரும்பாலான கார்பன் டைஆக்சைடு எரிமலையிலிருந்து வரும் மேக்மா மூலம் வெளியேற்றப்படுகிறது."
      },
      {
        "question": "கார்பன் டைஆக்சைடின் இயற்பியல் பண்புகளில் சரியானது எது?",
        "options": [
          "காற்றைவிட லேசானது",
          "எரிதலுக்குத் துணைபுரியும்",
          "நீரில் கரையாது",
          "நீல லிட்மஸ் தாளை சற்று சிவப்பாக மாற்றுகிறது"
        ],
        "answer": 3,
        "explanation": "கார்பன் டைஆக்சைடு நீரில் கரைந்து அமிலத்தன்மை வாய்ந்ததாகச் செயல்படுவதால், நீல லிட்மஸ் தாளை சிவப்பாக மாற்றுகிறது."
      },
      {
        "question": "திட நிலையிலுள்ள கார்பன் டைஆக்சைடு எவ்வாறு அழைக்கப்படுகிறது?",
        "options": [
          "உலர்பனிக்கட்டி (Dry Ice)",
          "பனிக்கட்டி",
          "கார்பானிக் அமிலம்",
          "திரவ கார்பன்"
        ],
        "answer": 0,
        "explanation": "திட நிலையிலுள்ள கார்பன் டைஆக்சைடு உலர் பனிக்கட்டி என்று அழைக்கப்படுகிறது."
      },
      {
        "question": "உலர் பனிக்கட்டி எவ்வகையான நிகழ்வுக்கு உட்படக்கூடியது?",
        "options": [
          "உருகுதல்",
          "ஆவியாதல்",
          "பதங்கமாதல்",
          "குளிர்தல்"
        ],
        "answer": 2,
        "explanation": "உலர் பனிக்கட்டி திடநிலையில் இருந்து நேரடியாக வாயுநிலைக்கு மாறும் பதங்கமாதலுக்கு (Sublimation) உட்படக்கூடியது."
      },
      {
        "question": "மெக்னீசியம் உலோகம் கார்பன் டைஆக்சைடுடன் வினைபுரியும் போது உருவாகும் விளைபொருள்கள் எவை?",
        "options": [
          "மெக்னீசியம் கார்பனேட் மற்றும் ஆக்சிஜன்",
          "மெக்னீசியம் ஆக்சைடு மற்றும் கார்பன்",
          "மெக்னீசியம் கார்பைடு",
          "எந்த வினையும் நடைபெறாது"
        ],
        "answer": 1,
        "explanation": "2Mg + CO2 -> 2MgO + C. மெக்னீசியம் அதனுடைய ஆக்சைடையும், கார்பனையும் தருகிறது."
      },
      {
        "question": "கார்பன் டைஆக்சைடு சோடியம் ஹைட்ராக்சைடு (NaOH) என்ற காரத்துடன் வினைபுரிந்து எதைத் தருகிறது?",
        "options": [
          "சோடியம் ஆக்சைடு மற்றும் நீர்",
          "சோடியம் கார்பனேட் மற்றும் நீர்",
          "சோடியம் பைகார்பனேட்",
          "சோடியம் ஹைட்ரைடு"
        ],
        "answer": 1,
        "explanation": "2NaOH + CO2 -> Na2CO3 + H2O. சோடியம் கார்பனேட்டையும் (உப்பு) நீரையும் தருகிறது."
      },
      {
        "question": "சுண்ணாம்பு நீரில் (Calcium hydroxide) கார்பன் டைஆக்சைடைச் செலுத்தும்போது அது பால் போல் மாறக் காரணம் என்ன?",
        "options": [
          "கால்சியம் ஆக்சைடு உருவாவதால்",
          "கரையாத கால்சியம் கார்பனேட் உருவாவதால்",
          "கால்சியம் பைகார்பனேட் உருவாவதால்",
          "கார்பானிக் அமிலம் உருவாவதால்"
        ],
        "answer": 1,
        "explanation": "சுண்ணாம்பு நீரில் கார்பன் டைஆக்சைடை செலுத்தும்போது கரையாத கால்சியம் கார்பனேட் (CaCO3) உருவாவதால் கரைசல் பால் போல் மாறுகிறது."
      },
      {
        "question": "சுண்ணாம்பு நீரில் அதிக அளவு கார்பன் டைஆக்சைடைச் செலுத்தும்போது பால் போன்ற நிறம் மறையக் காரணம் என்ன?",
        "options": [
          "கால்சியம் கார்பனேட் சிதைவடைவதால்",
          "கரையக்கூடிய கால்சியம் ஹைட்ரஜன் கார்பனேட் (Ca(HCO3)2) உருவாவதால்",
          "நீர் ஆவியாவதால்",
          "கால்சியம் ஆக்சைடு உருவாவதால்"
        ],
        "answer": 1,
        "explanation": "அதிகளவு கார்பன் டைஆக்சைடைச் செலுத்தும்போது கரையக்கூடிய கால்சியம் ஹைட்ரஜன் கார்பனேட் உருவாவதால் பால் போன்ற நிறம் மறைகிறது."
      },
      {
        "question": "வெள்ளிக் கோளின் (Venus) வளிமண்டலத்தில் கார்பன் டைஆக்சைடின் அளவு எவ்வளவு?",
        "options": [
          "21-25%",
          "45-50%",
          "78-80%",
          "96-97%"
        ],
        "answer": 3,
        "explanation": "வெள்ளிக் கோளின் வளிமண்டலத்தில் 96-97% கார்பன் டைஆக்சைடு உள்ளது."
      },
      {
        "question": "சூரிய குடும்பத்தில் மிகவும் வெப்பமான கோளாக வெள்ளி இருக்கக் காரணம் என்ன?",
        "options": [
          "அது சூரியனுக்கு மிக அருகில் இருப்பதால்",
          "அதன் வளிமண்டலத்தில் அதிக அளவு CO2 வெப்பத்தைத் தக்கவைத்துக்கொள்வதால்",
          "அங்கு எரிமலைகள் அதிகம் இருப்பதால்",
          "அதன் வளிமண்டலத்தில் ஆக்சிஜன் அதிகம் இருப்பதால்"
        ],
        "answer": 1,
        "explanation": "கார்பன் டைஆக்சைடின் அளவு 96-97% அதிகமாக இருப்பதால் வெள்ளியின் மேற்பரப்பால் வெப்பத்தைத்தக்கவைத்துக் கொள்ள முடிகிறது."
      },
      {
        "question": "காற்றேற்றப்பட்ட குளிர்பானங்கள் அல்லது மென்பானங்கள் (Aerated drinks) தயாரிக்கப் பயன்படும் வாயு எது?",
        "options": [
          "நைட்ரஜன்",
          "ஆக்சிஜன்",
          "கார்பன் டைஆக்சைடு",
          "ஆர்கான்"
        ],
        "answer": 2,
        "explanation": "காற்றேற்றப்பட்ட நீர் அல்லது சோடா நீர் தயாரிக்க அதிக அழுத்தத்தில் கார்பன் டைஆக்சைடு வாயு நீரில் கரைக்கப்படுகிறது."
      },
      {
        "question": "மேடை நிகழ்ச்சிகள் மற்றும் சினிமாக் காட்சிகளில் வெண்ணிற புகைமூட்டம் போன்ற தோற்றத்தை உருவாக்கப் பயன்படுவது எது?",
        "options": [
          "திரவ நைட்ரஜன்",
          "உலர் பனிக்கட்டி (திட CO2)",
          "திரவ ஆக்சிஜன்",
          "நீராவி"
        ],
        "answer": 1,
        "explanation": "உலர் பனிக்கட்டி மிகவும் குளிர்ச்சியாக இருப்பதால் காற்றிலுள்ள ஈரப்பதம் இதன் மீது விழுந்து அடர்த்தியான வெண்ணிற புகைமூட்டம் உருவாகிறது."
      },
      {
        "question": "சால்வே முறையில் (Solvay process) தயாரிக்கப்படும் சேர்மம் எது?",
        "options": [
          "சோடியம் குளோரைடு",
          "சோடியம் கார்பனேட்",
          "சோடியம் ஹைட்ராக்சைடு",
          "அம்மோனியா"
        ],
        "answer": 1,
        "explanation": "சால்வே முறையில் சோடியம் கார்பனேட் தயாரிக்க CO2 பயன்படுகிறது."
      },
      {
        "question": "கார்பன் டைஆக்சைடு அம்மோனியாவுடன் சேர்ந்து எந்த உரத்தைத் தயாரிக்கப் பயன்படுகிறது?",
        "options": [
          "பொட்டாஷ்",
          "நைட்ரேட்",
          "யூரியா",
          "சூப்பர் பாஸ்பேட்"
        ],
        "answer": 2,
        "explanation": "யூரியா போன்ற உரங்கள் தயாரிக்க கார்பன் டைஆக்சைடு அம்மோனியாவுடன் சேர்ந்து பயன்படுகிறது."
      },
      {
        "question": "வளிமண்டலத்திலுள்ள சில வாயு மூலக்கூறுகள் பூமியால் உமிழப்படும் அகச்சிவப்புக் கதிர்களை உறிஞ்சி மீண்டும் அனைத்துத் திசைகளிலும் அனுப்பி வெப்பநிலையைத் தக்கவைக்கும் நிகழ்வின் பெயர் என்ன?",
        "options": [
          "ஓசோன் படலச் சிதைவு",
          "அமில மழை",
          "பசுமை இல்ல விளைவு",
          "காலநிலை மாற்றம்"
        ],
        "answer": 2,
        "explanation": "அகச்சிவப்புக் கதிர்களை உறிஞ்சி வெப்பத்தைத் தக்கவைக்கும் இந்நிகழ்வு பசுமை இல்ல விளைவு (Greenhouse effect) எனப்படும்."
      },
      {
        "question": "கீழ்க்கண்டவற்றுள் பசுமை இல்ல வாயு (Greenhouse gas) அல்லாதது எது?",
        "options": [
          "கார்பன் டைஆக்சைடு (CO2)",
          "மீத்தேன் (CH4)",
          "நைட்ரஸ் ஆக்சைடு (N2O)",
          "ஆக்சிஜன் (O2)"
        ],
        "answer": 3,
        "explanation": "கார்பன் டைஆக்சைடு, நைட்ரஸ் ஆக்சைடு, மீத்தேன், குளோரோபுளுரோகார்பன் (CFC) போன்றவை பசுமை இல்ல வாயுக்கள் ஆகும். ஆக்சிஜன் அல்ல."
      },
      {
        "question": "வளிமண்டலத்தில் காற்று மாசுபடுத்திகளின் அளவு தொடர்ந்து அதிகரிப்பதால் புவியின் சராசரி வெப்பநிலை உயர்வது எவ்வாறு அழைக்கப்படுகிறது?",
        "options": [
          "அமில மழை",
          "உலக வெப்பமயமாதல்",
          "எல் நினோ",
          "பருவநிலை மாற்றம்"
        ],
        "answer": 1,
        "explanation": "பசுமை இல்ல விளைவு அதிகமாகி புவியின் வாயு மண்டல வெப்பநிலை சராசரியாக உயர்ந்து கொண்டே வருவது உலக வெப்பமயமாதல் (Global warming) எனப்படும்."
      },
      {
        "question": "உலக வெப்பமயமாதலின் விளைவுகளில் தவறானது எது?",
        "options": [
          "பனிமலைகள் மற்றும் பனிப்பாறைகள் உருகுகின்றன",
          "கடல் மட்டம் குறைகிறது",
          "வெள்ளம், மண் அரிப்பு அதிகரிக்கின்றன",
          "நீர் மற்றும் பூச்சிகளால் வரும் நோய்கள் பரவுகின்றன"
        ],
        "answer": 1,
        "explanation": "பனிமலைகள் உருகுவதால் கடல் மட்டம் உயரும், குறையாது."
      },
      {
        "question": "உலக வெப்பமயமாதலைத் தடுக்கும் முறைகளில் பொருந்தாதது எது?",
        "options": [
          "படிம எரிபொருள்களை குறைவாகப் பயன்படுத்துதல்",
          "அதிக எண்ணிக்கையில் மரங்களை நடுதல்",
          "CFC பயன்பாட்டைக் குறைத்தல்",
          "காடுகளை அதிக அளவில் அழித்தல்"
        ],
        "answer": 3,
        "explanation": "காடுகள் அழிவதைத் தடுத்தல் என்பதே உலக வெப்பமயமாதலைத் தடுக்கும் முறையாகும்."
      },
      {
        "question": "மாசற்ற தூய மழை நீரின் pH மதிப்பு என்ன?",
        "options": [
          "7.0",
          "5.6",
          "4.5",
          "8.2"
        ],
        "answer": 1,
        "explanation": "தூய மழை நீரின் pH மதிப்பு 5.6 ஆக இருக்கிறது. வளிமண்டலத்திலுள்ள கார்பன் டைஆக்சைடு கரைந்திருப்பதால் இது 7-ஐ விடக் குறைவாக உள்ளது."
      },
      {
        "question": "அமில மழையின் pH மதிப்பு எவ்வாறு இருக்கும்?",
        "options": [
          "5.6 ஐ விடக் குறைவு",
          "5.6 ஐ விட அதிகம்",
          "சரியாக 7.0",
          "8.0 முதல் 14.0 வரை"
        ],
        "answer": 0,
        "explanation": "அமில மழையின் pH மதிப்பு 5.6 ஐ விடக் குறைவாக இருக்கும்."
      },
      {
        "question": "காற்றில் கலக்கும் எந்த மாசுபடுத்திகள் மழைநீரில் கரைந்து அமில மழையை உருவாக்குகின்றன?",
        "options": [
          "கார்பன் மோனாக்சைடு மற்றும் ஆக்சிஜன்",
          "நைட்ரஜன் மற்றும் சல்பர் ஆக்சைடுகள்",
          "ஆர்கான் மற்றும் நியான்",
          "குளோரோபுளுரோகார்பன்கள்"
        ],
        "answer": 1,
        "explanation": "நைட்ரஜன், சல்பர் ஆக்சைடுகள் போன்றவை மழைநீரில் கரைந்து நைட்ரிக் அமிலம் மற்றும் சல்பூரிக் அமிலங்களை உருவாக்கி அமில மழையை உருவாக்குகின்றன."
      },
      {
        "question": "அமில மழையின் விளைவுகளில் தவறானது எது?",
        "options": [
          "மனிதர்களின் கண்களிலும், தோலிலும் எரிச்சலை உண்டாக்குகிறது",
          "விதை முளைத்தலையும், வளர்தலையும் ஊக்குவிக்கிறது",
          "மண்ணின் வளத்தை மாற்றுகிறது",
          "கட்டடங்கள் மற்றும் பாலங்களின் அரிப்பிற்குக் காரணமாகிறது"
        ],
        "answer": 1,
        "explanation": "அமில மழை விதை முளைத்தலையும், வளர்தலையும் தடை செய்கிறது என்பதே சரி."
      },
      {
        "question": "அமில மழையைத் தடுக்கும் வழிமுறைகளில் சிறந்த மாற்று எரிபொருள் எது?",
        "options": [
          "அதிக சல்பர் கொண்ட நிலக்கரி",
          "பெட்ரோல் மற்றும் டீசல்",
          "அழுத்தப்பட்ட இயற்கை வாயு (CNG)",
          "மரக்கட்டை"
        ],
        "answer": 2,
        "explanation": "பெட்ரோல், டீசல் பயன்பாட்டைக் குறைத்து அழுத்தப்பட்ட இயற்கை வாயுவைப் (CNG) பயன்படுத்துதல் அமில மழையைத் தடுக்கும் முறையாகும்."
      },
      {
        "question": "கூற்று (A): கடல், ஆறு, ஏரி போன்ற நீர் நிலைகளில் வாழும் உயிரினங்களுக்கு உயிர் வாழ்தல் சாத்தியமாகிறது.\nகாரணம் (R): ஆக்சிஜனானது நைட்ரஜனைவிட இருமடங்கு நீரில் அதிகமாகக் கரையும் தன்மை உடையது.",
        "options": [
          "A மற்றும் R இரண்டும் சரி, R என்பது A விற்கான சரியான விளக்கம்",
          "A மற்றும் R இரண்டும் சரி, R என்பது A விற்கான சரியான விளக்கமல்ல",
          "A சரி, R தவறு",
          "A தவறு, R சரி"
        ],
        "answer": 0,
        "explanation": "நீரில் ஆக்சிஜன் அதிகமாகக் கரைந்திருப்பதாலேயே நீர்வாழ் உயிரினங்கள் சுவாசித்து வாழ முடிகிறது."
      },
      {
        "question": "பொருத்துக: \n1) ஹேபர் முறை - a) சல்பூரிக் அமிலம்\n2) சால்வே முறை - b) அம்மோனியா\n3) அமில மழை - c) சோடியம் கார்பனேட்\n4) ஒளிச்சேர்க்கை - d) ஆக்சிஜன் வெளியேற்றம்",
        "options": [
          "1-b, 2-c, 3-a, 4-d",
          "1-c, 2-b, 3-d, 4-a",
          "1-a, 2-d, 3-c, 4-b",
          "1-d, 2-a, 3-b, 4-c"
        ],
        "answer": 0,
        "explanation": "ஹேபர் முறை - அம்மோனியா, சால்வே முறை - சோடியம் கார்பனேட், அமில மழை - சல்பூரிக்/நைட்ரிக் அமிலம், ஒளிச்சேர்க்கை - ஆக்சிஜன் வெளியேற்றம்."
      },
      {
        "question": "சரியா தவறா: நைட்ரஜன் தானாக எரியும், ஆனால் எரிதலுக்குத் துணைபுரியாது.",
        "options": [
          "சரி",
          "தவறு",
          "கூற இயலாது",
          "பகுதியளவு சரி"
        ],
        "answer": 1,
        "explanation": "நைட்ரஜன் தானாக எரிவதில்லை மற்றும் எரிதலுக்குத் துணைபுரிவதும் இல்லை என்பதே சரி."
      },
      {
        "question": "சரியா தவறா: சாதாரண வளிமண்டல அழுத்தத்தில் கார்பன் டைஆக்சைடு திரவ நிலையில் இருக்க இயலாது.",
        "options": [
          "சரி",
          "தவறு",
          "கூற இயலாது",
          "சில நேரங்களில் மட்டும்"
        ],
        "answer": 0,
        "explanation": "சாதாரண வளிமண்டல அழுத்தத்தில் கார்பன் டைஆக்சைடு திரவ நிலையில் இருக்க இயலாது. அது நேரடியாக வாயுவாக மாறும் (பதங்கமாதல்)."
      },
      {
        "question": "வாழ்க்கைச் சூழல் வினா: நீங்கள் மலை ஏறுபவர் (Mountaineer) என்றால், அதிக உயரத்திற்குச் செல்லும்போது உங்களுக்குத் தேவைப்படும் உருளையில் எந்த வாயு நிரப்பப்பட்டிருக்கும்?",
        "options": [
          "நைட்ரஜன்",
          "கார்பன் டைஆக்சைடு",
          "ஆக்சிஜன்",
          "ஆர்கான்"
        ],
        "answer": 2,
        "explanation": "ஆழ்கடலில் மூழ்குபவர்கள், மலை ஏறுபவர்கள் செயற்கை சுவாசத்திற்கு ஆக்சிஜன் உருளைகளைப் பயன்படுத்துவர்."
      },
      {
        "question": "வாழ்க்கைச் சூழல் வினா: உங்கள் வாகனத்தின் டயர்களில் காற்றிற்குப் பதிலாக நைட்ரஜனை ஏன் நிரப்ப அறிவுறுத்துகிறார்கள்?",
        "options": [
          "நைட்ரஜன் டயர்களை அதிக வெப்பமடையச் செய்யும்",
          "நைட்ரஜன் எளிதில் தீப்பற்றக்கூடியது",
          "நைட்ரஜன் மந்தத் தன்மை கொண்டது மற்றும் டயரின் அழுத்தத்தை நீண்ட காலம் சீராக வைக்கும்",
          "நைட்ரஜன் ஆக்சிஜனை விட மலிவானது"
        ],
        "answer": 2,
        "explanation": "நைட்ரஜன் மந்தத்தன்மை கொண்டது மற்றும் ஆக்சிஜனைப் போல் டயரின் உட்பகுதியை ஆக்ஸிஜனேற்றம் செய்து பாதிக்காது. மேலும் அழுத்தம் சீராக இருக்கும்."
      },
      {
        "question": "வாழ்க்கைச் சூழல் வினா: தாஜ்மஹால் போன்ற பளிங்குக்கல்லால் ஆன பழமையான கட்டடங்கள் மஞ்சள் நிறமாக மாறி அரிக்கப்பட முக்கியக் காரணம் என்ன?",
        "options": [
          "உலக வெப்பமயமாதல்",
          "அமில மழை",
          "ஓசோன் படலச் சிதைவு",
          "பசுமை இல்ல விளைவு"
        ],
        "answer": 1,
        "explanation": "காற்றில் கலக்கும் சல்பர் மற்றும் நைட்ரஜன் ஆக்சைடுகளால் ஏற்படும் அமில மழையே கட்டடங்கள் மற்றும் பாலங்களின் அரிப்பிற்குக் காரணமாகிறது."
      },
      {
        "question": "வாழ்க்கைச் சூழல் வினா: குளிர்சாதனப் பெட்டிகளில் (Refrigerators) மற்றும் ஆய்வகங்களில் பொருள்களை மிகக் குளிர்ந்த நிலையில் பாதுகாக்க பயன்படும் திரவம் எது?",
        "options": [
          "திரவ ஆக்சிஜன்",
          "திரவ நைட்ரஜன்",
          "கார்பானிக் அமிலம்",
          "திரவ அம்மோனியா"
        ],
        "answer": 1,
        "explanation": "திரவ நைட்ரஜன் குளிர்சாதனப் பெட்டிகளில் குளிரூட்டியாகப் பயன்படுகிறது."
      },
      {
        "question": "வாகனங்கள் மற்றும் தொழிற்சாலைகளிலிருந்து வெளியேற்றப்படும் எந்த வாயு புவி வெப்பமயமாதல் மற்றும் அமில மழை இரண்டிற்கும் தொடர்புடையதல்ல?",
        "options": [
          "கார்பன் டைஆக்சைடு",
          "சல்பர் டைஆக்சைடு",
          "நைட்ரஜன் ஆக்சைடுகள்",
          "ஆர்கான்"
        ],
        "answer": 3,
        "explanation": "ஆர்கான் ஒரு மந்த வாயு, இது எவ்வித மாசையும் ஏற்படுத்துவதில்லை."
      },
      {
        "question": "கீழ்க்கண்டவற்றுள் ஆக்சிஜனைப் பற்றிய சரியான கூற்று எது? (புத்தக வினா)",
        "options": [
          "முழுமையாக எரியும் வாயு",
          "பகுதியளவு எரியும் வாயு",
          "எரிதலுக்குத் துணைபுரியாத வாயு",
          "எரிதலுக்குத் துணைபுரியும் வாயு"
        ],
        "answer": 3,
        "explanation": "ஆக்சிஜன் தனித்து எரியும் தன்மை அற்றது, ஆனால் இது எரிதலுக்குத் துணைபுரியும் வாயுவாகும்."
      },
      {
        "question": "காற்றேற்றம் செய்யப்பட்ட நீரில் __________ உள்ளது. (புத்தக வினா)",
        "options": [
          "காற்று",
          "ஆக்சிஜன்",
          "கார்பன் டைஆக்சைடு",
          "நைட்ரஜன்"
        ],
        "answer": 2,
        "explanation": "காற்றேற்றம் செய்யப்பட்ட நீர் (Aerated water) என்பது அதிக அழுத்தத்தில் கார்பன் டைஆக்சைடு வாயு நீரில் கரைந்துள்ள பொருளாகும்."
      },
      {
        "question": "சால்வே முறை __________ உற்பத்தி செய்ய பயன்படுகிறது. (புத்தக வினா)",
        "options": [
          "சுண்ணாம்பு நீர்",
          "காற்றேற்றம் செய்யப்பட்ட நீர்",
          "வாலை வடி நீர்",
          "சோடியம் கார்பனேட்"
        ],
        "answer": 3,
        "explanation": "சால்வே முறையில் சோடியம் கார்பனேட் தயாரிக்க கார்பன் டைஆக்சைடு பயன்படுகிறது."
      },
      {
        "question": "கார்பன் டைஆக்சைடு நீருடன் சேர்ந்து __________ மாற்றுகிறது. (புத்தக வினா)",
        "options": [
          "நீலலிட்மசை சிவப்பாக",
          "சிவப்பு லிட்மசை நீலமாக",
          "நீல லிட்மசை மஞ்சளாக",
          "லிட்மசுடன் வினைபுரிவதில்லை"
        ],
        "answer": 0,
        "explanation": "கார்பன் டைஆக்சைடு அமிலத்தன்மை வாய்ந்தது. எனவே இது நீல லிட்மஸ் தாளைச் சிவப்பாக மாற்றுகிறது."
      },
      {
        "question": "அசோட் எனப்படுவது எது? (புத்தக வினா)",
        "options": [
          "ஆக்சிஜன்",
          "நைட்ரஜன்",
          "சல்பர்",
          "கார்பன் டைஆக்சைடு"
        ],
        "answer": 1,
        "explanation": "ஆன்டன் லவாய்சியர் நைட்ரஜனுக்கு 'அசோட்' என்ற பெயரைப் பரிந்துரைத்தார்."
      },
      {
        "question": "_____________ அத்தியாவசியமான உயிர் எனப்படுகிறது. (கோடிட்ட இடம்)",
        "options": [
          "நைட்ரஜன்",
          "கார்பன்",
          "ஆக்சிஜன்",
          "மீத்தேன்"
        ],
        "answer": 2,
        "explanation": "C.W. ஷீலே ஆக்சிஜனைக் கண்டறிந்தபோது அதனை நெருப்புக்காற்று என்றும் 'அத்தியாவசியமான உயிர்' என்றும் அழைத்தார்."
      },
      {
        "question": "நைட்ரஜன் காற்றை விட ___________. (கோடிட்ட இடம்)",
        "options": [
          "கனமானது",
          "இலேசானது",
          "மிகவும் அதிக அடர்த்தியானது",
          "ஒப்பிட முடியாதது"
        ],
        "answer": 1,
        "explanation": "நைட்ரஜனின் இயற்பியல் பண்புகளின்படி, இது காற்றை விட சிறிதளவு இலேசானது."
      },
      {
        "question": "_________ உரமாகப் பயன்படுகிறது. (கோடிட்ட இடம்/பொருத்துக)",
        "options": [
          "நைட்ரஜன்",
          "ஆக்சிஜன்",
          "உலர்பனி",
          "ஆர்கான்"
        ],
        "answer": 0,
        "explanation": "நைட்ரஜன் (அம்மோனியா தயாரிப்பு வழியாக) தாவரங்களுக்குத் தேவையான உரமாகப் பயன்படுகிறது."
      },
      {
        "question": "உலர்பனி _________ ஆகப் பயன்படுகிறது. (கோடிட்ட இடம்)",
        "options": [
          "வெடிபொருள்",
          "குளிர்விப்பான்",
          "எரிபொருள்",
          "உரம்"
        ],
        "answer": 1,
        "explanation": "திட கார்பன் டைஆக்சைடு உலர் பனிக்கட்டி எனப்படுகிறது. இது குளிர்விப்பானாகப் (Refrigerant) பயன்படுகிறது."
      },
      {
        "question": "இரும்பை நீரேறிய இரும்பு ஆக்சைடாக மாற்றும் நிகழ்வு ___________ எனப்படும். (கோடிட்ட இடம்)",
        "options": [
          "பதங்கமாதல்",
          "நடுநிலையாக்கல்",
          "துருப்பிடித்தல்",
          "ஒளிச்சேர்க்கை"
        ],
        "answer": 2,
        "explanation": "காற்று மற்றும் ஈரப்பதத்தின் முன்னிலையில் இரும்பு அதனுடைய நீரேறிய ஆக்சைடாக மாறும் நிகழ்வு துருப்பிடித்தல் (Rusting) எனப்படும்."
      },
      {
        "question": "பொருத்துக: \n1) நைட்ரஜன் - a) குளிர்விப்பான்\n2) ஆக்சிஜன் - b) தீயணைப்பான்\n3) கார்பன் டைஆக்சைடு - c) உயிரினங்களின் சுவாசித்தல்\n4) உலர்பனி - d) உரம்",
        "options": [
          "1-d, 2-c, 3-b, 4-a",
          "1-b, 2-a, 3-d, 4-c",
          "1-c, 2-d, 3-a, 4-b",
          "1-a, 2-b, 3-c, 4-d"
        ],
        "answer": 0,
        "explanation": "நைட்ரஜன் - உரம், ஆக்சிஜன் - உயிரினங்களின் சுவாசித்தல், கார்பன் டைஆக்சைடு - தீயணைப்பான், உலர்பனி - குளிர்விப்பான்."
      },
      {
        "question": "உலோகங்கள் மற்றும் அலோகங்களுடன் ஆக்சிஜன் வினைபுரியும் போது ஏற்படும் மாற்றம் என்ன?",
        "options": [
          "உலோகங்கள் அமில ஆக்சைடுகளையும், அலோகங்கள் கார ஆக்சைடுகளையும் தருகின்றன",
          "உலோகங்கள் கார ஆக்சைடுகளையும், அலோகங்கள் அமில ஆக்சைடுகளையும் தருகின்றன",
          "இரண்டும் நடுநிலை ஆக்சைடுகளைத் தருகின்றன",
          "இரண்டும் எந்த ஆக்சைடையும் தருவதில்லை"
        ],
        "answer": 1,
        "explanation": "உலோக ஆக்சைடுகள் பொதுவாக காரத்தன்மை உடையவை. அலோக ஆக்சைடுகள் அமிலத்தன்மை வாய்ந்தவை."
      },
      {
        "question": "எரிமலையிலிருந்து வெளிப்படும் வாயுக்களிலும், நிலக்கரியை எரிக்கும்பொழுது வெளியாகும் வாயுக்களிலும் உள்ள தனிமம் எது?",
        "options": [
          "நைட்ரஜன்",
          "ஆக்சிஜன்",
          "ஹீலியம்",
          "ஆர்கான்"
        ],
        "answer": 0,
        "explanation": "எரிமலையிலிருந்து வெளிப்படும் வாயுக்களிலும், நிலக்கரியை எரிக்கும்பொழுது வெளியாகும் வாயுக்களிலும் நைட்ரஜன் உள்ளது."
      },
      {
        "question": "கார்பன் டைஆக்சைடின் அழுத்தத்தை அதிகரிக்கும் போது அது எந்த நிலைக்கு மாறுகிறது?",
        "options": [
          "நேரடியாகத் திண்மமாக மட்டும்",
          "திரவமாகலாம் மற்றும் திண்மமாகவும் மாறலாம்",
          "வாயுவாகவே இருக்கும்",
          "பிளாஸ்மாவாக மாறும்"
        ],
        "answer": 1,
        "explanation": "அதிக அழுத்தத்தைப் பயன்படுத்தி கார்பன் டைஆக்சைடைத் திரவமாக்கலாம் மற்றும் திண்மமாகவும் மாற்றலாம்."
      },
      {
        "question": "ஒளிச்சேர்க்கை (Photosynthesis) வினையில் பயன்படுத்தப்படும் ஆற்றல் எது?",
        "options": [
          "மின் ஆற்றல்",
          "வேதி ஆற்றல்",
          "சூரியனிலிருந்து பெறப்படும் ஆற்றல்",
          "வெப்ப ஆற்றல்"
        ],
        "answer": 2,
        "explanation": "தாவரங்கள் குளோரோபில் மற்றும் சூரிய ஒளியைப் (சூரிய ஆற்றல்) பயன்படுத்தி குளுக்கோஸ் தயாரிக்கின்றன."
      },
      {
        "question": "கால்சியம் உலோகம் நைட்ரஜனுடன் வினைபுரிந்து உருவாக்கும் சேர்மத்தின் வாய்ப்பாடு என்ன?",
        "options": [
          "CaN",
          "Ca2N3",
          "Ca3N2",
          "CaN2"
        ],
        "answer": 2,
        "explanation": "3Ca + N2 -> Ca3N2 (கால்சியம் நைட்ரைடு)."
      },
      {
        "question": "நைட்ரஜனைப் போல லிட்மஸுடன் நடுநிலைத் தன்மையுடன் (Neutral) காணப்படும் மற்றொரு வாயு எது?",
        "options": [
          "கார்பன் டைஆக்சைடு",
          "சல்பர் டைஆக்சைடு",
          "ஆக்சிஜன்",
          "நைட்ரஜன் டைஆக்சைடு"
        ],
        "answer": 2,
        "explanation": "ஆக்சிஜனைப் போலவே, நைட்ரஜனும் லிட்மஸுடன் நடுநிலைத் தன்மையுடன் காணப்படுகிறது."
      },
      {
        "question": "உணவுத் தானியங்கள், பழங்கள் போன்றவற்றைப் பதப்படுத்தப் பயன்படும் வாயு எது?",
        "options": [
          "கார்பன் மோனாக்சைடு",
          "கார்பன் டைஆக்சைடு",
          "ஆக்சிஜன்",
          "ஹைட்ரஜன்"
        ],
        "answer": 1,
        "explanation": "கார்பன் டைஆக்சைடு உணவு தானியங்கள், பழங்கள் போன்றவற்றைப் பதப்படுத்தப் பயன்படுகிறது."
      },
      {
        "question": "எண்ணெய் மற்றும் வாயுக்கள் உயிரிய சிதைவுக்குள்ளாகும்பொழுதும் (bio-degradation) உருவாகும் வாயு எது?",
        "options": [
          "ஆக்சிஜன்",
          "கார்பன் டைஆக்சைடு",
          "நைட்ரஜன்",
          "ஆர்கான்"
        ],
        "answer": 1,
        "explanation": "எண்ணெய் மற்றும் வாயுக்கள் உயிரிய சிதைவுக்குள்ளாகும்பொழுதும் கார்பன் டைஆக்சைடு உருவாகிறது."
      },
      {
        "question": "வளிமண்டலத்தில் கார்பன் டைஆக்சைடின் அளவு அதிகரிப்பதால் ஏற்படும் முக்கிய விளைவு என்ன?",
        "options": [
          "ஓசோன் படல உருவாக்கம்",
          "புவியின் வெப்பநிலை குறைதல்",
          "உலக வெப்பமயமாதல்",
          "நைட்ரஜன் சுழற்சி அதிகரித்தல்"
        ],
        "answer": 2,
        "explanation": "மனிதனால் உருவாக்கப்படும் கார்பன் டைஆக்சைடு வளிமண்டலத்தில் அதிகமாகி உலகெங்கிலும் வெப்பநிலையை உயர்த்துவதால் பூமியின் வெப்பநிலை உயர்கிறது (உலக வெப்பமயமாதல்)."
      }
    ]
  },
  "material": {
    "sections": [
      {
        "title": "பாடச் சுருக்கம் (நினைவில் கொள்க)",
        "content": "• ஆக்சிஜன் இயற்கையில் சிலிக்கேட்டுகள், கார்பனேட்டுகள் மற்றும் நீராகக் காணப்படுகிறது. இது தனித்த நிலையில் வளிமண்டலக் காற்றின் ஒரு பகுதியாகவும் உள்ளது.\n• ஆக்சிஜன் நிறமற்றது, மணமற்றது மற்றும் நீரில் ஓரளவுக்குக் கரையக்கூடியது. காற்றைவிட அடர்த்தியானது.\n• மெக்னீசியம், இரும்பு, சோடியம் போன்ற உலோகங்கள் ஆக்சிஜனுடன் சேர்ந்து எரிந்து கார ஆக்சைடுகளைத் தருகின்றன.\n• பாக்டீரியாக்கள் வளிமண்டல நைட்ரஜனை நீரில் நேரடியாக கரையக்கூடிய நைட்ரஜன் சேர்மங்களாக மாற்றுகின்றன.\n• சாதாரண சூழ்நிலைகளில் நைட்ரஜன் வினைதிறனற்றதாக இருந்தாலும் உயர் வெப்பநிலை, அழுத்தம் அல்லது வினைவேகமாற்றியின் முன்னிலையில் பல்வேறு தனிமங்களுடன் வினைபுரிகின்றது.\n• சாதாரண வளிமண்டல அழுத்தத்தில் கார்பன் டைஆக்சைடு திரவ நிலையில் இருக்க இயலாது. இது இயற்கையில் கார்பனேட்டாக உள்ளது.\n• கார்பன் டைஆக்சைடு அமிலத்தன்மை கொண்டது. மேலும், தெளிந்த சுண்ணாம்பு நீரைப் பால் போல் மாற்றக் கூடியது.\n• கார்பன் டைஆக்சைடு தீயணைக்கும் கருவிகளில் பயன்படுகிறது.\n• உலக வெப்பமயமாதல் என்பது வளிமண்டலத்தின் சராசரி வெப்பநிலை உயர்வதைக் குறிக்கிறது அல்லது பூமி வெப்பமடைவதைக் குறிக்கிறது.\n• கார்பன் டைஆக்சைடு, மீத்தேன், நைட்ரஸ் ஆக்சைடு, குளோரோபுளூரோகார்பன் ஆகியவை பசுமை இல்ல வாயுக்கள் ஆகும்."
      },
      {
        "title": "அறிமுகம் மற்றும் காற்றின் இயைபு",
        "content": "நமது புவிக் கோளத்தைச் சுற்றியுள்ள வாயுக்களின் கலவையே காற்று ஆகும். காற்றில் 78.09% நைட்ரஜனும், 20.95% ஆக்சிஜனும், 0.93% ஆர்கானும், 0.04% கார்பன் டைஆக்சைடும் சிறிதளவு இதர வாயுக்களும் அடங்கியுள்ளன.\nநாம் ஆக்சிஜனை சுவாசித்து கார்பன் டைஆக்சைடை வெளியிடுகிறோம். தாவரங்கள் கார்பன் டைஆக்சைடை ஒளிச்சேர்க்கைக்குப் பயன்படுத்திக் கொண்டு ஆக்சிஜனை வெளியிடுகின்றன. தொழிற்சாலைகள் மற்றும் வாகனங்களிலிருந்து வெளியேறும் கார்பன் மோனாக்சைடு மற்றும் சல்பர் டைஆக்சைடு போன்ற வாயுக்கள் உலக வெப்பமயமாதல் மற்றும் அமில மழைக்குக் காரணமாகின்றன."
      },
      {
        "title": "ஆக்சிஜன் (Oxygen) - கண்டுபிடிப்பு மற்றும் பெயர்க்காரணம்",
        "content": "1772ஆம் ஆண்டு ஸ்வீடன் நாட்டைச் சேர்ந்த வேதியியலாளர் C.W.ஷீலே ஆக்சிஜனைக் கண்டறிந்தார். இது எரிதலுக்குத் துணை புரிந்ததால் இதனை 'நெருப்புக்காற்று' என்றும், 'அத்தியாவசியமான உயிர்' என்றும் அவர் அழைத்தார். 1774ஆம் ஆண்டு பிரிட்டன் அறிவியலாளர் ஜோசப் பிரிஸ்ட்லி என்பவரும் ஆக்சிஜனைக் கண்டறிந்தார். லவாய்சியர் இதற்கு ஆக்சிஜன் என்று பெயரிட்டார். கிரேக்க மொழியில் 'ஆக்சிஜன்ஸ்' (Oxygenes) என்றால் ‘அமில உருவாக்கி’ என்று பொருள்."
      },
      {
        "title": "ஆக்சிஜன் பரவல்",
        "content": "ஹைட்ரஜன் மற்றும் ஹீலியத்திற்கு அடுத்தபடியாக இந்த அண்டத்தில் பரவலாக மூன்றாவதாகக் காணப்படும் தனிமம் ஆக்சிஜன். வளிமண்டலத்தில் ஈரணு வாயு மூலக்கூறாக (O2) உள்ளது. மேல் அடுக்குகளில் ஓசோன் (O3) மூவணு மூலக்கூறாக உள்ளது. புவியோட்டில் சிலிக்கேட்டுகளாகவும், உலோக ஆக்சைடுகளாகவும் உள்ளது.\n\nஆக்சிஜனின் சதவீதம்:\nவளிமண்டலக் காற்று: 21% (தனித்த நிலை)\nநீர்: 88 – 90% (இணைந்த நிலை)\nதாவரங்கள் மற்றும் விலங்குகள்: 60 – 70% (இணைந்த நிலை)\nதாதுக்கள்: 45 – 50% (இணைந்த நிலை)\n\nபுவியோட்டிலுள்ள தனிமங்கள் (படம் 11.1): O (46.6%), Si (27.7%), Al (8.1%), Fe (5.0%), Ca (3.6%), Na (2.8%), K (2.6%), Mg (2.1%)."
      },
      {
        "title": "ஆக்சிஜனின் இயற்பியல் மற்றும் வேதிப்பண்புகள்",
        "content": "இயற்பியல் பண்புகள்: நிறமற்ற, மணமற்ற, சுவையற்ற வாயு. வெப்பம், மின்சாரத்தை கடத்தாது. குளிர்ந்த நீரில் கரையும். காற்றை விட கனமானது. எரிதலுக்குத் துணைபுரியும்.\n\nவேதிப்பண்புகள்:\n1. எரிதல்: தனித்து எரியாது, ஆனால் பிற பொருள்களின் எரிதலுக்குத் துணை புரியும்.\n2. உலோகங்களுடன் வினை: உலோக ஆக்சைடுகளை (காரத்தன்மை) தருகிறது. (எ.கா: 4Na + O2 -> 2Na2O). பொட்டாசியம் அறைவெப்பநிலையிலும், மெக்னீசியம்/கால்சியம் வெப்பப்படுத்தும்போதும், இரும்பு/தாமிரம் அதிக வெப்பத்திலும் வினைபுரியும். தங்கம், பிளாட்டினம் வினைபுரியாது.\n3. அலோகங்களுடன் வினை: அமிலத்தன்மை வாய்ந்த அலோக ஆக்சைடுகளை உருவாக்கும். (C->CO2, N->NO, S->SO2, P->P2O3/P2O5).\n4. ஹைட்ரோ கார்பன்களுடன் வினை: கார்பன் டைஆக்சைடு, நீராவி, வெப்பம் மற்றும் ஒளியைத் தருகிறது.\n5. துருப்பிடித்தல்: இரும்பு ஈரப்பதமான காற்றில் நீரேறிய இரும்பு (II) ஆக்சைடாக (துரு - Fe2O3.XH2O) மாறும் நிகழ்வு."
      },
      {
        "title": "ஆக்சிஜனின் பயன்கள்",
        "content": "• ஆக்சி-அசிட்டிலின் உருளைகளில் வெல்டிங் செய்யப் பயன்படுகிறது.\n• எஃகிலுள்ள கார்பன் மாசை நீக்கப் பயன்படுகிறது.\n• விலங்குகள், தாவரங்கள் சுவாசத்திற்கு உதவுகிறது.\n• ராக்கெட்டுகளில் எரிபொருளாகப் பயன்படுகிறது.\n• ஆழ்கடலில் மூழ்குபவர்கள், மலை ஏறுபவர்கள், விண்வெளி வீரர், நோயாளிகளுக்கு செயற்கை சுவாசத்திற்குப் பயன்படுகிறது.\n• கரித்தூளுடன் இணைந்து வெடிபொருள் தயாரிக்கப்படுகிறது.\n• மெத்தனால் மற்றும் அம்மோனியா தயாரிக்கப் பயன்படுகிறது."
      },
      {
        "title": "நைட்ரஜன் (Nitrogen) - அறிமுகம் மற்றும் பரவல்",
        "content": "அனைத்து உயிரினங்களின் (புரோட்டீன்கள், நியூக்ளிக் அமிலங்கள்) அடிப்படைக் கட்டமைப்புப் பொருள். 1772ல் கார்ல் வில்கம் ஷீலே என்பவரால் பிரித்தெடுக்கப்பட்டது. 'நைட்ரோன்' மற்றும் 'ஜீன்' (நான் நைட்டரை உருவாக்குகிறேன்) என்பதிலிருந்து உருவானது. லவாய்சியர் இதற்கு 'அசோட்' (Azote - வாழ்வு இல்லாதது) எனப் பெயரிட்டார்.\n\nபரவல்: மனித உடலில் நான்காவதாக அதிகம் காணப்படும் தனிமம் (3%). அண்டத்தில் ஏழாவது இடம். சனிக்கோளின் துணைக்கோளான டைட்டனில் 98% உள்ளது. தாதுக்களாக பொட்டாசியம் நைட்ரேட் (நைட்டர் - KNO3), சோடியம் நைட்ரேட் (சில்லி சால்ட் பீட்டர் - NaNO3) கிடைக்கிறது."
      },
      {
        "title": "நைட்ரஜனின் இயற்பியல் மற்றும் வேதிப்பண்புகள்",
        "content": "இயற்பியல் பண்புகள்: நிறமற்ற, மணமற்ற, சுவையற்ற வாயு. காற்றை விட இலேசானது. நீரில் சிறிதளவே கரையும். மிகக் குறைந்த வெப்பநிலையில் நீரைப் போன்ற திரவமாகவும், உறையும்போது வெண்மையான திண்மமாகவும் மாறும். லிட்மஸுடன் நடுநிலைத் தன்மை.\n\nவேதிப்பண்புகள்:\n1. வேதிவினை: சாதாரண நிலையில் வினைபுரியாது. அதிக வெப்பம்/அழுத்தத்தில் வினைபுரியும்.\n2. எரிதல்: தானாக எரியாது, எரிதலுக்குத் துணைபுரியாது.\n3. உலோகங்களுடன் வினை: உலோக நைட்ரைடுகளைத் தரும் (3Ca + N2 -> Ca3N2).\n4. அலோகங்களுடன் வினை: அதிக வெப்பநிலையில் சேர்மங்களைத் தரும் (3H2 + N2 -> 2NH3)."
      },
      {
        "title": "நைட்ரஜனின் பயன்கள் மற்றும் நிலைநிறுத்தம்",
        "content": "பயன்கள்: திரவ நைட்ரஜன் குளிரூட்டியாகப் பயன்படுகிறது. மந்தத் தன்மை நிலவச் செய்கிறது. அம்மோனியா தயாரிக்க (ஹேபர் முறை) பயன்படுகிறது. வாகன டயர்களில் நிரப்பப்படுகிறது. பாதரசம் ஆவியாகாமல் தடுக்க வெப்பநிலைமானிகளில் பயன்படுகிறது. வெடிபொருள்கள் (TNT), உணவு பதப்படுத்துதல், பல்புகளில் பயன்படுகிறது.\n\nநைட்ரஜன் நிலைநிறுத்தம்: காற்றில் உள்ள தனிம நைட்ரஜனை தாவரங்கள் நேரடியாகப் பயன்படுத்த முடியாது. காற்றில் உள்ள நைட்ரஜனை நீரில் கரையும் நைட்ரஜன் சேர்மங்களாக (நைட்ரேட்டுகளாக) மாற்றும் முறை நைட்ரஜன் நிலைநிறுத்தம் எனப்படும்."
      },
      {
        "title": "கார்பன் டைஆக்சைடு (CO2) - பரவல் மற்றும் பண்புகள்",
        "content": "பரவல்: வளிமண்டலத்தில் 0.03% உள்ளது. சுவாசித்தல், நொதித்தல், எரிமலை மேக்மா, உயிரிய சிதைவு போன்றவற்றால் வெளியாகிறது.\n\nஇயற்பியல் பண்புகள்: நிறமற்ற, மணமற்ற, காற்றைவிட கனமான வாயு. எரிதலுக்குத் துணைபுரியாது. நீரில் கரையும், நீல லிட்மஸை சிவப்பாக மாற்றும் (அமிலத்தன்மை). அதிக அழுத்தத்தில் திரவமாக்கலாம். திட CO2 'உலர் பனிக்கட்டி' எனப்படும் (பதங்கமாதல் பண்பு)."
      },
      {
        "title": "கார்பன் டைஆக்சைடின் வேதிப்பண்புகள் மற்றும் பயன்கள்",
        "content": "வேதிப்பண்புகள்:\n1. எரிதல்: தானாக எரியாது, துணைபுரியாது.\n2. உலோகங்களுடன்: சோடியம், பொட்டாசியத்துடன் கார்பனேட்டுகளைத் தரும் (4Na + 3CO2 -> 2Na2CO3 + C). மெக்னீசியத்துடன் ஆக்சைடைத் தரும்.\n3. காரத்துடன்: சோடியம் கார்பனேட்டையும் (உப்பு) நீரையும் தரும் (2NaOH + CO2 -> Na2CO3 + H2O).\n4. சுண்ணாம்பு நீருடன்: கரையாத கால்சியம் கார்பனேட் உருவாவதால் பால் போல் மாறும் (Ca(OH)2 + CO2 -> CaCO3 + H2O). அதிக CO2 செலுத்தினால் கரையக்கூடிய Ca(HCO3)2 உருவாகி நிறம் மறையும்.\n\nபயன்கள்: காற்றேற்றப்பட்ட குளிர்பானங்கள் (சோடா நீர்), உலர் பனிக்கட்டி குளிர்விப்பானாக/மேடைப் புகைமூட்டத்திற்கு, தீயணைப்பான்களில், சால்வே முறையில் சோடியம் கார்பனேட் தயாரிக்க, யூரியா தயாரிக்க, உணவு பதப்படுத்த."
      },
      {
        "title": "பசுமை இல்ல விளைவு, புவி வெப்பமயமாதல் மற்றும் அமில மழை",
        "content": "பசுமை இல்ல விளைவு: வளிமண்டலத்திலுள்ள பசுமை இல்ல வாயுக்கள் (CO2, N2O, மீத்தேன், CFC) பூமியால் உமிழப்படும் அகச்சிவப்புக் கதிர்களை உறிஞ்சி மீண்டும் அனுப்பி வெப்பநிலையைத் தக்கவைக்கும் நிகழ்வு.\nஉலக வெப்பமயமாதல்: பசுமை இல்ல வாயுக்களின் அதிகரிப்பால் புவியின் சராசரி வெப்பநிலை உயரும் நிகழ்வு. விளைவுகள்: பனிமலைகள் உருகுதல், வெள்ளம், பவளப்பாறைகள் அழிவு, நோய்கள் பரவல். தடுக்கும் முறைகள்: படிம எரிபொருள்களை குறைத்தல், மரம் நடுதல், CFC குறைத்தல்.\n\nஅமில மழை: தூய மழை நீரின் pH 5.6. தொழிற்சாலை கழிவுகளான நைட்ரஜன், சல்பர் ஆக்சைடுகள் மழைநீரில் கரைந்து நைட்ரிக், சல்பூரிக் அமிலங்களை உருவாக்குகின்றன. இதுவே அமில மழை. விளைவுகள்: தோல் எரிச்சல், விதை முளைத்தல் தடை, நீர்வாழ் உயிரினங்கள் அழிவு, கட்டடங்கள்/பாலங்கள் அரிப்பு. தடுக்கும் முறை: CNG பயன்படுத்துதல், மாற்று எரிபொருள்."
      },
      {
        "title": "உங்களுக்குத் தெரியுமா? (தகவல் பேழை)",
        "content": "• ஆக்சிஜனுக்கு தானாகவே தீப்பற்றி எரியும் தன்மை இருந்தால் நமது வளிமண்டலத்திலுள்ள ஆக்சிஜன் முழுவதும் எரிய ஒரு தீக்குச்சி மட்டுமே போதுமானதாக இருக்கும்.\n• ஆக்சிஜனானது நைட்ரஜனைவிட இருமடங்கு நீரில் அதிகமாகக் கரையும் தன்மை உடையது. இது நீர்வாழ் உயிரினங்களுக்கு அவசியம்.\n• பதங்கமாதல்: திடப்பொருளை வெப்பப்படுத்தி திரவ நிலைக்குச் செல்லாமல் நேரடியாக வாயு நிலைக்கு மாற்றும் முறை.\n• வெள்ளிக் கோளின் வளிமண்டலத்தில் 96-97% CO2 உள்ளது. எனவே இது வெப்பத்தைத் தக்கவைத்துக்கொள்கிறது. மேற்பரப்பு வெப்பநிலை 462°C. இதுவே சூரிய குடும்பத்தில் மிகவும் வெப்பமான கோள்.\n• காற்றேற்றப்பட்ட நீர் என்பது அதிக அழுத்தத்தில் கார்பன் டைஆக்சைடு வாயு நீரில் கரைந்துள்ள பொருளாகும். இது சோடா நீர் எனப்படும்."
      },
      {
        "title": "கலைச்சொற்கள்",
        "content": "• வளிமண்டலம்: பூமியைச் சுற்றியுள்ள வாயுக்களால் ஆன கவசம்.\n• நைட்ரஜன் நிலைநிறுத்தம்: வளிமண்டல நைட்ரஜனை நைட்ரஜன் சேர்மங்களாக மாற்றும் முறை.\n• உலகவெப்பமயமாதல்: வளிமண்டல வெப்பநிலையில் ஏற்படும் சராசரி உயர்வு.\n• பசுமை இல்ல விளைவு: பசுமை இல்ல வாயுக்களால் சூரிய வெப்பம் கவரப்படுவதால் ஏற்படும் பூமியின் வெப்பநிலை உயர்வு.\n• ஹேபர் முறை: நைட்ரஜன், ஹைட்ரஜனைக் கொண்டு அம்மோனியாவைத் தயாரிக்கும் முறை.\n• ஆக்சிஜென்ஸ்: அமில உருவாக்கி (கிரேக்கச் சொல்).\n• சோடா நீர்: அழுத்தத்தைப் பயன்படுத்தி CO2-ஐ நீரில் கரைத்து உருவாக்கப்படும் நீர்.\n• பதங்கமாதல்: திடப்பொருள் நேரடியாக வாயு நிலைக்கு மாறும் முறை."
      },
      {
        "title": "பாட பின்புற வினாக்கள் (மதிப்பீடு)",
        "content": "I. சரியான விடையைத் தேர்ந்தெடுத்து எழுதுக.\n1. கீழ்க்கண்டவற்றுள் ஆக்சிஜனைப் பற்றிய சரியான கூற்று எது? - விடை: ஈ) எரிதலுக்குத் துணைபுரியும் வாயு\n2. காற்றேற்றம் செய்யப்பட்ட நீரில் __________ உள்ளது. - விடை: இ) கார்பன் டைஆக்சைடு\n3. சால்வே முறை __________ உற்பத்தி செய்ய பயன்படுகிறது. - விடை: ஈ) சோடியம் கார்பனேட்\n4. கார்பன் டைஆக்சைடு நீருடன் சேர்ந்து __________ மாற்றுகிறது. - விடை: அ) நீலலிட்மசை சிவப்பாக\n5. அசோட் எனப்படுவது எது? - விடை: ஆ) நைட்ரஜன்\n\nII. கோடிட்ட இடங்களை நிரப்புக.\n1. _ஆக்சிஜன்_ அத்தியாவசியமான உயிர் எனப்படுகிறது.\n2. நைட்ரஜன் காற்றை விட _இலேசானது_.\n3. _நைட்ரஜன் / அம்மோனியா_ உரமாகப் பயன்படுகிறது.\n4. உலர்பனி _குளிர்விப்பான்_ ஆகப் பயன்படுகிறது.\n5. இரும்பை நீரேறிய இரும்பு ஆக்சைடாக மாற்றும் நிகழ்வு _துருப்பிடித்தல்_ எனப்படும்.\n\nIII. பொருத்துக.\nநைட்ரஜன் - உரம்\nஆக்சிஜன் - உயிரினங்களின் சுவாசித்தல்\nகார்பன் டைஆக்சைடு - தீயணைப்பான்\nஉலர்பனி - குளிர்விப்பான்"
      }
    ]
  }
}